log_reg_dre/__init__.py
log_reg_dre/data_generation.py
log_reg_dre/density_ratio_estimation.py
log_reg_dre/estimators.py
log_reg_dre/loss_functions.py
log_reg_dre/main.py
log_reg_dre/models.py
log_reg_dre-0.1.8.dist-info/LICENSE
log_reg_dre-0.1.8.dist-info/METADATA
log_reg_dre-0.1.8.dist-info/WHEEL
log_reg_dre-0.1.8.dist-info/top_level.txt
log_reg_dre-0.1.8.dist-info/RECORD
