Metadata-Version: 2.1
Name: log-reg-dre
Version: 0.1.8
Summary: Combines logistic regression for estimating density ratios with RU regression to mitigate distributional shift
Author: Sean Zhang
Author-email: szhang120@gmail.com
Classifier: Programming Language :: Python :: 3
Classifier: License :: OSI Approved :: MIT License
Classifier: Operating System :: OS Independent
Requires-Python: >=3.6
License-File: LICENSE
Requires-Dist: numpy
Requires-Dist: torch
Requires-Dist: matplotlib
Requires-Dist: scikit-learn
